[
    {
        "inputs": [],
        "name": "FeeExceedMaxPercentage",
        "type": "error"
    },
    {
        "anonymous": false,
        "inputs": [
            {
                "indexed": false,
                "internalType": "address",
                "name": "_newBorrowerOperationsAddress",
                "type": "address"
            }
        ],
        "name": "BorrowerOperationsAddressChanged",
        "type": "event"
    },
    {
        "anonymous": false,
        "inputs": [
            {
                "indexed": false,
                "internalType": "address",
                "name": "_tokenAddress",
                "type": "address"
            },
            {
                "indexed": false,
                "internalType": "bool",
                "name": "_isColl",
                "type": "bool"
            },
            {
                "indexed": false,
                "internalType": "enum IBase.PoolType",
                "name": "_poolType",
                "type": "uint8"
            },
            {
                "indexed": false,
                "internalType": "uint256",
                "name": "_updatedAmount",
                "type": "uint256"
            }
        ],
        "name": "PoolValueUpdated",
        "type": "event"
    },
    {
        "anonymous": false,
        "inputs": [
            {
                "indexed": false,
                "internalType": "address",
                "name": "_priceFeedAddress",
                "type": "address"
            }
        ],
        "name": "PriceFeedAddressChanged",
        "type": "event"
    },
    {
        "anonymous": false,
        "inputs": [
            {
                "indexed": false,
                "internalType": "address",
                "name": "_newStabilityPoolAddress",
                "type": "address"
            }
        ],
        "name": "StabilityPoolManagerAddressChanged",
        "type": "event"
    },
    {
        "anonymous": false,
        "inputs": [
            {
                "indexed": false,
                "internalType": "address",
                "name": "_newTroveManagerAddress",
                "type": "address"
            }
        ],
        "name": "TroveManagerAddressChanged",
        "type": "event"
    },
    {
        "inputs": [
            {
                "internalType": "address",
                "name": "_tokenAddress",
                "type": "address"
            },
            {
                "internalType": "bool",
                "name": "_isColl",
                "type": "bool"
            },
            {
                "internalType": "enum IBase.PoolType",
                "name": "_poolType",
                "type": "uint8"
            },
            {
                "internalType": "uint256",
                "name": "_amount",
                "type": "uint256"
            }
        ],
        "name": "addValue",
        "outputs": [],
        "stateMutability": "nonpayable",
        "type": "function"
    },
    {
        "inputs": [],
        "name": "checkRecoveryMode",
        "outputs": [
            {
                "internalType": "bool",
                "name": "isInRecoveryMode",
                "type": "bool"
            },
            {
                "internalType": "uint256",
                "name": "TCR",
                "type": "uint256"
            },
            {
                "internalType": "uint256",
                "name": "entireSystemColl",
                "type": "uint256"
            },
            {
                "internalType": "uint256",
                "name": "entireSystemDebt",
                "type": "uint256"
            }
        ],
        "stateMutability": "view",
        "type": "function"
    },
    {
        "inputs": [],
        "name": "getEntireSystemColl",
        "outputs": [
            {
                "internalType": "uint256",
                "name": "entireSystemColl",
                "type": "uint256"
            }
        ],
        "stateMutability": "view",
        "type": "function"
    },
    {
        "inputs": [],
        "name": "getEntireSystemDebt",
        "outputs": [
            {
                "internalType": "uint256",
                "name": "entireSystemDebt",
                "type": "uint256"
            }
        ],
        "stateMutability": "view",
        "type": "function"
    },
    {
        "inputs": [
            {
                "internalType": "address",
                "name": "_tokenAddress",
                "type": "address"
            },
            {
                "internalType": "bool",
                "name": "_isColl",
                "type": "bool"
            },
            {
                "internalType": "enum IBase.PoolType",
                "name": "_poolType",
                "type": "uint8"
            }
        ],
        "name": "getValue",
        "outputs": [
            {
                "internalType": "uint256",
                "name": "",
                "type": "uint256"
            }
        ],
        "stateMutability": "view",
        "type": "function"
    },
    {
        "inputs": [
            {
                "internalType": "address",
                "name": "_tokenAddress",
                "type": "address"
            },
            {
                "internalType": "bool",
                "name": "_isColl",
                "type": "bool"
            },
            {
                "internalType": "enum IBase.PoolType",
                "name": "_poolType",
                "type": "uint8"
            },
            {
                "internalType": "uint256",
                "name": "_amount",
                "type": "uint256"
            }
        ],
        "name": "subtractValue",
        "outputs": [],
        "stateMutability": "nonpayable",
        "type": "function"
    },
    {
        "inputs": [
            {
                "internalType": "address",
                "name": "_tokenAddress",
                "type": "address"
            },
            {
                "internalType": "bool",
                "name": "_isCool",
                "type": "bool"
            },
            {
                "internalType": "enum IBase.PoolType",
                "name": "_fromType",
                "type": "uint8"
            },
            {
                "internalType": "enum IBase.PoolType",
                "name": "_toType",
                "type": "uint8"
            },
            {
                "internalType": "uint256",
                "name": "_amount",
                "type": "uint256"
            }
        ],
        "name": "transferBetweenTypes",
        "outputs": [],
        "stateMutability": "nonpayable",
        "type": "function"
    },
    {
        "inputs": [
            {
                "internalType": "address",
                "name": "_receiver",
                "type": "address"
            },
            {
                "internalType": "address",
                "name": "_tokenAddress",
                "type": "address"
            },
            {
                "internalType": "bool",
                "name": "_isColl",
                "type": "bool"
            },
            {
                "internalType": "enum IBase.PoolType",
                "name": "_poolType",
                "type": "uint8"
            },
            {
                "internalType": "uint256",
                "name": "_amount",
                "type": "uint256"
            }
        ],
        "name": "withdrawalValue",
        "outputs": [],
        "stateMutability": "nonpayable",
        "type": "function"
    }
]
